LICENSE
MANIFEST.in
README.md
pyproject.toml
setup.py
pynisher/__init__.py
pynisher/exceptions.py
pynisher/py.typed
pynisher/pynisher.py
pynisher/support.py
pynisher/util.py
pynisher/win_errcodes.py
pynisher.egg-info/PKG-INFO
pynisher.egg-info/SOURCES.txt
pynisher.egg-info/dependency_links.txt
pynisher.egg-info/requires.txt
pynisher.egg-info/top_level.txt
pynisher/limiters/__init__.py
pynisher/limiters/limiter.py
pynisher/limiters/linux.py
pynisher/limiters/mac.py
pynisher/limiters/windows.py