Metadata-Version: 2.1
Name: pynisher
Version: 1.0.6
Summary: A library to limit the resources used by functions using subprocesses
Home-page: https://github.com/automl/pynisher
Author: ('Stefan Falkner, Christina Hernandez-Wunsch, Samuel Mueller,Matthias Feurer, Francisco Rivera, Eddie Bergman and Rene Sass',)
Author-email: feurerm@informatik.uni-freiburg.de
License: MIT
Keywords: resources
Classifier: License :: OSI Approved :: BSD License
Classifier: Natural Language :: English
Classifier: Programming Language :: Python :: 3.7
Classifier: Programming Language :: Python :: 3.8
Classifier: Programming Language :: Python :: 3.9
Classifier: Programming Language :: Python :: 3.10
Requires-Python: >=3.7
Provides-Extra: test
License-File: LICENSE
